<?xml version="1.0" encoding="utf-8" ?>
<Language DisplayName="English" Culture="en" Version="0.13">
  <Messages>
    <Error>Error</Error>
    <TouchscreenNotFoundTitle>Error</TouchscreenNotFoundTitle>
    <TouchscreenNotFound>Can not find Touchscreen!</TouchscreenNotFound>
    <CannotFindTouchInputProviderMessage>Can not find GestureSign.TouchInputProvider.exe.Try to redownload or reinstall GestureSign.</CannotFindTouchInputProviderMessage>
  </Messages>
  <TrayMenu>
    <TrainingMode>Training Mode</TrainingMode>
    <Disable>Disable GestureSign</Disable>
    <ControlPanel>Control Panel</ControlPanel>
    <Exit>Exit</Exit>
    <BalloonTipTitle>GestureSign</BalloonTipTitle>
    <BalloonTip>GestureSign has started.</BalloonTip>
  </TrayMenu>
</Language>